reddit_bot/__init__.py
reddit_bot/bot.py
reddit_bot/cli.py
reddit_bot_vg-0.0.2.dist-info/LICENSE
reddit_bot_vg-0.0.2.dist-info/METADATA
reddit_bot_vg-0.0.2.dist-info/WHEEL
reddit_bot_vg-0.0.2.dist-info/top_level.txt
reddit_bot_vg-0.0.2.dist-info/RECORD
